cvbase/__init__.py
cvbase/conversion.py
cvbase/decorators.py
cvbase/image.py
cvbase/io.py
cvbase/opencv.py
cvbase/progress.py
cvbase/timer.py
cvbase/version.py
cvbase/video.py
cvbase/visualize.py
cvbase/det/__init__.py
cvbase/det/bbox_ops.py
cvbase/det/eval.py
cvbase/det/labels.py
cvbase/optflow/__init__.py
cvbase/optflow/io.py
cvbase/optflow/visualize.py
cvbase-0.5.5.dist-info/METADATA
cvbase-0.5.5.dist-info/RECORD
cvbase-0.5.5.dist-info/WHEEL
cvbase-0.5.5.dist-info/top_level.txt
tests/__init__.py
tests/test_conversion.py
tests/test_decorators.py
tests/test_det.py
tests/test_image.py
tests/test_io.py
tests/test_optflow.py
tests/test_progress.py
tests/test_timer.py
tests/test_video.py
