Metadata-Version: 2.1
Name: cvbase
Version: 0.5.5
Summary: Utils for computer vision research
Home-page: https://github.com/hellock/cvbase
Author: Kai Chen
Author-email: chenkaidev@gmail.com
License: MIT
Keywords: computer vision
Platform: UNKNOWN
Classifier: Development Status :: 4 - Beta
Classifier: License :: OSI Approved :: MIT License
Classifier: Operating System :: OS Independent
Classifier: Programming Language :: Python :: 2
Classifier: Programming Language :: Python :: 2.7
Classifier: Programming Language :: Python :: 3
Classifier: Programming Language :: Python :: 3.4
Classifier: Programming Language :: Python :: 3.5
Classifier: Programming Language :: Python :: 3.6
Classifier: Topic :: Utilities
Requires-Dist: numpy (>=1.11.1)
Requires-Dist: pyyaml
Requires-Dist: six
Requires-Dist: terminaltables
